dm_app/__init__.py
dm_app/audit/__init__.py
dm_app/audit/admin.py
dm_app/audit/apps.py
dm_app/audit/decorator.py
dm_app/audit/managers.py
dm_app/audit/managerscd.py
dm_app/audit/models.py
dm_app/audit/serializers.py
dm_app/audit/services.py
dm_app/audit/urls.py
dm_app/audit/views.py
dm_app/audit/migrations/0001_initial.py
dm_app/audit/migrations/__init__.py
dm_app/audit/migrations_cd/__init__.py
dm_app/audit/migrations_cd/migration_001_20230715_111850_audit_event_log_creation.py
dm_app/audit/tests/__init__.py
dm_app_audit-1.0.1.dist-info/licenses/LICENSE
dm_app_audit-1.0.1.dist-info/METADATA
dm_app_audit-1.0.1.dist-info/WHEEL
dm_app_audit-1.0.1.dist-info/top_level.txt
dm_app_audit-1.0.1.dist-info/RECORD
